{
    "posts": [
        {
            "id": 1,
            "postAt": "2018-04-19T10:59-0500",
            "title": "Titile of this article",
            "content": "Test test",
            "user": {
                "id": "002",
                "name": "Lauren Levinson",
                "avatar": "https://loremflickr.com/320/320/women"
            }
        }
    ],
    "comments": [
        {
            "id": 1,
            "body": "Winter is coming... 🥶🥶🥶",
            "postId": 1,
            "postAt": "2018-10-19T10:59-0500",
            "user": {
                "id": "001",
                "name": "Jon Snow",
                "avatar": "https://loremflickr.com/320/320/men"
            }
        },
        {
            "id": 2,
            "body": "You know nothing Jon snow",
            "postId": 1,
            "postAt": "2018-11-19T11:59-0500",
            "user": {
                "id": "002",
                "name": "Lauren Levinson",
                "avatar": "https://loremflickr.com/320/320/women"
            }
        }
    ],
    "profile": {
        "name": "typicode"
    },
    "lottos": {
        "seller": {
            "id": "00001",
            "name": "Jon Snow",
            "currentLocation": {
                "lat": "",
                "lng": "",
                "name": "",
                "distance": 200
            },
            "specialConditions": ""
        },
        "headerline": {
            "number": "123456",
            "price": "30 M"
        },
        "feature1": [
            {
                "data": 111111,
                "amount": 1,
                "isFeature": true,
                "featureType": "three"
            },
            {
                "data": 111112,
                "amount": 1,
                "isFeature": true,
                "featureType": "three"
            },
            {
                "data": 111113,
                "amount": 1,
                "isFeature": true,
                "featureType": "three"
            }
        ],
        "feature2": [
            {
                "data": 111115,
                "amount": 1,
                "isFeature": true,
                "featureType": "two"
            },
            {
                "data": 111116,
                "amount": 1,
                "isFeature": true,
                "featureType": "two"
            },
            {
                "data": 111117,
                "amount": 1,
                "isFeature": true,
                "featureType": "two"
            }
        ],
        "feature3": [
            {
                "data": 111118,
                "amount": 1,
                "isFeature": true,
                "featureType": "two"
            },
            {
                "data": 111119,
                "amount": 1,
                "isFeature": true,
                "featureType": "two"
            },
            {
                "data": 111120,
                "amount": 1,
                "isFeature": true,
                "featureType": "two"
            }
        ],
        "data": [
            {
                "data": 111111,
                "amount": 1,
                "isFeature": true,
                "featureType": "three"
            },
            {
                "data": 111112,
                "amount": 1,
                "isFeature": true,
                "featureType": "three"
            },
            {
                "data": 111113,
                "amount": 1,
                "isFeature": true,
                "featureType": "three"
            },
            {
                "data": 111115,
                "amount": 1,
                "isFeature": true,
                "featureType": "two"
            },
            {
                "data": 111116,
                "amount": 1,
                "isFeature": true,
                "featureType": "two"
            },
            {
                "data": 111117,
                "amount": 1,
                "isFeature": true,
                "featureType": "two"
            },
            {
                "data": 111118,
                "amount": 1,
                "isFeature": true,
                "featureType": "two"
            },
            {
                "data": 111119,
                "amount": 1,
                "isFeature": true,
                "featureType": "two"
            },
            {
                "data": 111120,
                "amount": 1,
                "isFeature": true,
                "featureType": "two"
            }
        ]
    }
}